manim_revealjs/__init__.py
manim_revealjs/plugin.py
manim_revealjs/presentationscene.py
manim_revealjs-1.0.2.dist-info/LICENSE
manim_revealjs-1.0.2.dist-info/METADATA
manim_revealjs-1.0.2.dist-info/WHEEL
manim_revealjs-1.0.2.dist-info/top_level.txt
manim_revealjs-1.0.2.dist-info/RECORD
