Metadata-Version: 2.1
Name: manim-revealjs
Version: 1.0.2
Summary: Generate Manim animations for presentations using Reveal.js
Home-page: https://github.com/rickdw/manim-revealjs
License: UNKNOWN
Project-URL: Bug Tracker, https://github.com/rickdw/manim-revealjs/issues
Platform: UNKNOWN
Classifier: Programming Language :: Python :: 3
Classifier: License :: OSI Approved :: MIT License
Classifier: Operating System :: OS Independent
Requires-Python: >=3.6
License-File: LICENSE
